osc_client/__init__.py
osc_client/main.py
osc_client-0.0.1.dist-info/LICENSE
osc_client-0.0.1.dist-info/METADATA
osc_client-0.0.1.dist-info/WHEEL
osc_client-0.0.1.dist-info/top_level.txt
osc_client-0.0.1.dist-info/RECORD
