Metadata-Version: 2.1
Name: osc-client
Version: 0.0.1
Summary: A Python client for OpenStreetCam.org (OSC) API utilization.
Home-page: UNKNOWN
Author: d33bs
Author-email: d33bs@users.noreply.github.com
License: Apache 2.0
Keywords: osc openstreetcam streetview roadview api requests
Platform: UNKNOWN
Classifier: License :: OSI Approved :: Apache Software License
Classifier: Operating System :: OS Independent
Requires-Python: >=3.6
Requires-Dist: requests
